xaal/__init__.py
xaal/tuya/__init__.py
xaal/tuya/__main__.py
xaal/tuya/devices.py
xaal/tuya/gw.py
xaal/tuya/pytuya/__init__.py
xaal_tuya-0.3.1.dist-info/METADATA
xaal_tuya-0.3.1.dist-info/WHEEL
xaal_tuya-0.3.1.dist-info/top_level.txt
xaal_tuya-0.3.1.dist-info/RECORD
